pygrambank/__init__.py
pygrambank/__main__.py
pygrambank/api.py
pygrambank/bib.py
pygrambank/cldf.py
pygrambank/cli_util.py
pygrambank/contributors.py
pygrambank/features.py
pygrambank/issues.py
pygrambank/sheet.py
pygrambank/util.py
pygrambank/commands/__init__.py
pygrambank/commands/check.py
pygrambank/commands/check_conflicts.py
pygrambank/commands/check_encoding.py
pygrambank/commands/cleanmojibake.py
pygrambank/commands/conflicts.py
pygrambank/commands/describe.py
pygrambank/commands/download_issues.py
pygrambank/commands/enrichgb20.py
pygrambank/commands/features.py
pygrambank/commands/fix.py
pygrambank/commands/fixhg.py
pygrambank/commands/issue1786.py
pygrambank/commands/issue1797.py
pygrambank/commands/issues.py
pygrambank/commands/merge_conflicts.py
pygrambank/commands/merge_contrib.py
pygrambank/commands/move_resolved_conflicts.py
pygrambank/commands/new.py
pygrambank/commands/recode.py
pygrambank/commands/remove_empty.py
pygrambank/commands/roundtrip.py
pygrambank/commands/sourcelookup.py
pygrambank/commands/stats.py
pygrambank/commands/updatefeatures.py
pygrambank/commands/wiki.py
pygrambank-2.1.dist-info/LICENSE
pygrambank-2.1.dist-info/METADATA
pygrambank-2.1.dist-info/WHEEL
pygrambank-2.1.dist-info/entry_points.txt
pygrambank-2.1.dist-info/top_level.txt
pygrambank-2.1.dist-info/RECORD
