Metadata-Version: 2.1
Name: pygrambank
Version: 2.1
Summary: A python library to curate Grambank data
Home-page: https://github.com/grambank/pygrambank
Author: Robert Forkel
Author-email: robert_:forkel@eva.mpg.de
License: Apache 2.0
Platform: any
Classifier: Development Status :: 2 - Pre-Alpha
Classifier: Intended Audience :: Developers
Classifier: License :: OSI Approved :: Apache Software License
Classifier: Natural Language :: English
Classifier: Operating System :: OS Independent
Classifier: Programming Language :: Python :: 3
Classifier: Programming Language :: Python :: 3.7
Classifier: Programming Language :: Python :: 3.8
Classifier: Programming Language :: Python :: 3.9
Classifier: Programming Language :: Python :: 3.10
Classifier: Programming Language :: Python :: 3.11
Classifier: Programming Language :: Python :: Implementation :: CPython
Classifier: Programming Language :: Python :: Implementation :: PyPy
Requires-Python: >=3.7
License-File: LICENSE
Requires-Dist: clldutils (>=3.6)
Requires-Dist: cldfcatalog
Requires-Dist: csvw (>=3.1.3)
Requires-Dist: pycldf (>=1.29)
Requires-Dist: xlrd
Requires-Dist: openpyxl (==2.4.8)
Requires-Dist: pyglottolog (>=2.0)
Requires-Dist: tqdm
Requires-Dist: beautifulsoup4 (>=4.9.1)
Requires-Dist: ftfy
Requires-Dist: html5lib
Provides-Extra: dev
Requires-Dist: flake8 ; extra == 'dev'
Requires-Dist: wheel ; extra == 'dev'
Requires-Dist: twine ; extra == 'dev'
Provides-Extra: test
Requires-Dist: pytest (>=5.4) ; extra == 'test'
Requires-Dist: pytest-mock ; extra == 'test'
Requires-Dist: pytest-cov ; extra == 'test'
Requires-Dist: coverage (>=4.2) ; extra == 'test'
